web3_validator/__init__.py
web3_validator-1.2.0.dist-info/LICENSE
web3_validator-1.2.0.dist-info/METADATA
web3_validator-1.2.0.dist-info/WHEEL
web3_validator-1.2.0.dist-info/top_level.txt
web3_validator-1.2.0.dist-info/RECORD
